kobold/__init__.py
kobold/assertions.py
kobold/doubles.py
kobold/hash_functions.py
kobold/html.py
kobold/response.py
kobold/swap.py
kobold/compare/__init__.py
kobold/compare/assertions.py
kobold/compare/hints.py
kobold-12.16.0.dist-info/licenses/LICENSE
kobold-12.16.0.dist-info/METADATA
kobold-12.16.0.dist-info/WHEEL
kobold-12.16.0.dist-info/top_level.txt
kobold-12.16.0.dist-info/RECORD
