Metadata-Version: 2.4
Name: kobold
Version: 12.16.0
Summary: Various tools for working with, and writing tests in Python
Author-email: "Krieghan J. Riley" <krieghan.riley@gmail.com>
Project-URL: Repository, https://github.com/krieghan/kobold_python.git
Project-URL: Homepage, https://github.com/krieghan/kobold_python.git
Project-URL: Documentation, https://github.com/krieghan/kobold_python.git
Keywords: test,mock,double,compare
Classifier: Development Status :: 5 - Production/Stable
Classifier: Intended Audience :: Developers
Classifier: License :: OSI Approved :: MIT License
Classifier: Operating System :: OS Independent
Classifier: Programming Language :: Python :: 3
Classifier: Topic :: Software Development :: Testing
Classifier: Topic :: Software Development :: Testing :: Mocking
Classifier: Topic :: Software Development :: Testing :: Unit
Requires-Python: >=3.0
License-File: LICENSE
Requires-Dist: python-dateutil
Provides-Extra: dev
Requires-Dist: flake8; extra == "dev"
Dynamic: license-file
